json2email
