Metadata-Version: 1.1
Name: json2email
Version: 0.0.6
Summary: Takes a jinja2 template and some json and sends an email
Home-page: https://github.com/sanger-pathogens/json2email
Author: Ben Taylor
Author-email: ben.taylor@sanger.ac.uk
License: GPLv3
Platform: UNKNOWN
Classifier: License :: OSI Approved :: GNU General Public License v3 (GPLv3)
Classifier: Programming Language :: Python
Classifier: Development Status :: 4 - Beta
Classifier: Topic :: Communications :: Email
Classifier: Topic :: System :: Monitoring
Classifier: Topic :: Utilities
